jira_time_machine/__init__.py
jira_time_machine/jira_time_machine.py
jira_time_machine/utils.py
jira_time_machine-0.0.1.dist-info/METADATA
jira_time_machine-0.0.1.dist-info/WHEEL
jira_time_machine-0.0.1.dist-info/licenses/LICENSE
jira_time_machine-0.0.1.dist-info/RECORD
