Metadata-Version: 2.4
Name: jira-time-machine
Version: 0.0.1
Summary: Jira Time Machine gives you the state of your Jira project at any time in its history
Project-URL: Homepage, https://github.com/ingoweiss/jira-time-machine
Project-URL: Bug Tracker, https://github.com/ingoweiss/jira-time-machine/issues
Project-URL: Repository, https://github.com/ingoweiss/jira-time-machine.git
Project-URL: Changelog, https://github.com/ingoweiss/jira-time-machine/blob/master/CHANGELOG.md
Project-URL: Documentation, https://github.com/ingoweiss/jira-time-machine
Author-email: Ingo Weiss <ingo@ingoweiss.com>
License: MIT License
License-File: LICENSE
Classifier: Development Status :: 3 - Alpha
Classifier: Intended Audience :: Developers
Classifier: Intended Audience :: Information Technology
Classifier: License :: OSI Approved :: MIT License
Classifier: Natural Language :: English
Classifier: Operating System :: OS Independent
Classifier: Programming Language :: Python :: 3
Classifier: Programming Language :: Python :: 3.8
Classifier: Programming Language :: Python :: 3.9
Classifier: Programming Language :: Python :: 3.10
Classifier: Programming Language :: Python :: 3.11
Classifier: Programming Language :: Python :: 3.12
Classifier: Topic :: Software Development
Requires-Python: >=3.8
Requires-Dist: jira>=3.4.0
Requires-Dist: mock>=4.0.0
Requires-Dist: numpy>=1.21.0
Requires-Dist: pandas>=1.3.0
Requires-Dist: pytest-mock>=3.6.0
Requires-Dist: pytest>=7.0.0
Requires-Dist: tqdm>=4.64.0
